pyhelper/__init__.py
pyhelper/misc.py
pyhelper_misc-2.0.0.dist-info/LICENSE
pyhelper_misc-2.0.0.dist-info/METADATA
pyhelper_misc-2.0.0.dist-info/WHEEL
pyhelper_misc-2.0.0.dist-info/top_level.txt
pyhelper_misc-2.0.0.dist-info/RECORD
