Metadata-Version: 2.1
Name: pyhelper-misc
Version: 2.0.0
Summary: Python Library Containing Generic Utilities and Helper Functions
Home-page: https://github.com/shubhamraj2202/pyhelper
Author: Shubham Raj
Author-email: shubhamraj2202@gmail.com
Project-URL: Bug Reports, https://github.com/shubhamraj2202/pyhelper/issues
License-File: LICENSE
